{
  "Isabella Rodriguez": {
    "maze": "the_ville",
    "x": 78,
    "y": 19
  },
  "Giorgio Rossi": {
    "maze": "the_ville",
    "x": 87,
    "y": 24
  },
  "Carlos Gomez": {
    "maze": "the_ville",
    "x": 108,
    "y": 32
  },
  "Klaus Mueller": {
    "maze": "the_ville",
    "x": 115,
    "y": 47
  },
  "Maria Lopez": {
    "maze": "the_ville",
    "x": 123,
    "y": 57
  },
  "Ayesha Khan": {
    "maze": "the_ville",
    "x": 109,
    "y": 44
  },
  "Tamara Taylor": {
    "maze": "the_ville",
    "x": 56,
    "y": 70
  },
  "Carmen Ortiz": {
    "maze": "the_ville",
    "x": 55,
    "y": 70
  },
  "Eddy Lin": {
    "maze": "the_ville",
    "x": 96,
    "y": 55
  }
}